<?xml version="1.0" encoding="utf-8"?>
<story season="A" episode="13" scene="f">
	<teller>
		<default>De noite, Mel chega em casa.</default>
	</teller>
	<talk character="Edmont">
		<default>Fugiu de novo?!</default>
	</talk>
	<talk character="Kat">
		<default>Não, dessa vez deram alta.</default>
	</talk>
	<talk character="Angely">
		<default>E o CD?</default>
	</talk>
	<talk character="Mel">
		<default>Grego.</default>
	</talk>
	<talk character="Derik">
		<default>Que???</default>
	</talk>
	<teller>
		<default>Dara chega.</default>
	</teller>
	<talk character="Kat">
		<default>Atrasou.</default>
	</talk>
	<talk character="Dara">
		<default>Desculpe, Denise pensa um pouco quando quer.</default>
	</talk>
	<talk character="Mel">
		<default>Tudo bem, o problema é o seguinte: o CD que eu tava guardando...</default>
	</talk>
	<talk character="Edmont">
		<default>Escondendo.</default>
	</talk>
	<teller>
		<default>Mel encara Edmont, que devolve o ato.</default>
	</teller>
	<talk character="Mel">
		<default>É uma espécie de diário.</default>
	</talk>
	<talk character="Angely">
		<default>De quem?</default>
	</talk>
	<talk character="Mel">
		<default>Não sei. Não consegui ler.</default>
	</talk>
	<talk character="Edmont">
		<default>Como não conseguiu?</default>
	</talk>
	<talk character="Derik">
		<default>Ela acabou de dizer que tá em grego.</default>
	</talk>
	<talk character="Dara">
		<default>E o que vamos fazer?</default>
	</talk>
	<talk character="Kat">
		<default>Alguém se ofereceu pra traduzir em troca de falarmos o nosso passado.</default>
	</talk>
	<talk character="Edmont">
		<default>Não vou falar com nenhum jornalista.</default>
	</talk>
	<talk character="Mel">
		<default>Não é jornalista. É um vampiro.</default>
	</talk>
	<talk character="Edmont">
		<irony>Claro, não convidou ele pra jantar, não?</irony>
	</talk>
	<talk character="Kat">
		<default>É o cara que me seqüestrou...</default>
	</talk>
	<talk character="Edmont">
		<irony>Melhor ainda!</irony>
	</talk>
	<talk character="Angely">
		<default>Pensa bem, ele não matou Kat quando pôde.</default>
	</talk>
	<teller>
		<default>A campainha toca.</default>
	</teller>
	<talk character="Dara">
		<default>Eu atendo.</default>
	</talk>
	<teller>
		<default>Ela desce a escada e abre a porta.</default>
	</teller>
	<talk character="Dara">
		<default>Sim?</default>
	</talk>
	<talk character="Zenon">
		<default>Preciso falar com Melody, ela tá aí?</default>
	</talk>
	<talk character="Dara">
		<default>Está, quer que eu chame?</default>
	</talk>
	<talk character="Zenon">
		<default>Claro. Posso esperar na sala?</default>
	</talk>
	<teller>
		<default>Dara pára um pouco e ri.</default>
	</teller>
	<talk character="Dara">
		<default>Isso não é só educação.</default>
	</talk>
	<talk character="Zenon">
		<default>Como assim?</default>
	</talk>
	<talk character="Dara">
		<default>Os amigos chamam ela de Mel.</default>
	</talk>
	<talk character="Zenon">
		<default>E você, quem é?</default>
	</talk>
	<talk character="Dara">
		<default>Como vou dizer se não sei de você?</default>
	</talk>
	<talk character="Zenon">
		<default>É claro que sabe. Acabou de me provar isso.</default>
	</talk>
	<talk character="Dara">
		<default>Volte ao meio-dia e pode entrar.</default>
	</talk>
	<teller>
		<default>Ela fecha a porta e volta ao escritório.</default>
	</teller>
	<talk character="Edmont">
		<default>Quem era?</default>
	</talk>
	<talk character="Dara">
		<default>Repórter.</default>
	</talk>
	<talk character="Mel">
		<default>Quem é contra e quem é a favor do contarmos a ele?</default>
	</talk>
	<talk character="Kat">
		<default>Eu não acho que bom.</default>
	</talk>
	<talk character="Edmont">
		<default>Sonhou duas vezes com "malfeitos" dele, certo?</default>
	</talk>
	<talk character="Kat">
		<default>Ahã.</default>
	</talk>
	<talk character="Edmont">
		<default>Contra.</default>
	</talk>
	<talk character="Dara">
		<default>Não vejo nada de errado.</default>
	</talk>
	<talk character="Angely">
		<default>Nem eu.</default>
	</talk>
	<talk character="Mel">
		<default>Que ele pode fazer?</default>
	</talk>
	<talk character="Kat">
		<default>Último voto... Derik.</default>
	</talk>
	<talk character="Derik">
		<default>Eu, eu... Voto contra.</default>
	</talk>
	<talk character="Mel">
		<default>Agradeceria se desse o seu voto e não o da Kat.</default>
	</talk>
	<talk character="Derik">
		<default>Eu só acho que não devemos confiar em vampiros.</default>
	</talk>
	<talk character="Mel">
		<default>Tá, merda, empatou de novo.</default>
	</talk>
	<talk character="Angely">
		<default>De novo?</default>
	</talk>
	<talk character="Mel">
		<default>Eu e Kat já sabíamos o que vocês dois iam falar, logo estaria empatado.</default>
	</talk>
	<talk character="Kat">
		<default>Não, não, não, eu já sabia que o Derik ia votar contra.</default>
	</talk>
	<talk character="Angely">
		<default>Tudo bem, como vamos fazer o desempate?</default>
	</talk>
	<talk character="Edmont">
		<default>Sorteio.</default>
		<teller>todos olham pra ele</teller>
		<default>Alguma idéia melhor?</default>
	</talk>
	<talk character="Dara">
		<default>Vamos esperar Kat sonhar alguma coisa e amanhã de tarde vemos isso.</default>
	</talk>
	<talk character="Derik">
		<default>Acho que deveríamos ir num centro e perguntar pra Djanira!</default>
	</talk>
	<talk character="Mel">
		<default>Tem três pessoas pra decidir qual das três idéias.</default>
	</talk>
	<talk character="Angely">
		<default>Prefiro a da Dara. A do Edmont parece meio afobada e a do Derik é, no mínimo, idiota.</default>
	</talk>
	<talk character="Kat">
		<default>Sinto muito, Derik, mas eu concordo com o Angely.</default>
	</talk>
	<talk character="Derik">
		<default>Acham que tava falando sério? Também prefiro a idéia da Dara.</default>
	</talk>
	<talk character="Mel">
		<default>Desculpa, Edmont, mas você perdeu.</default>
	</talk>
	<talk character="Edmont">
		<default>Tudo bem. Mais nada pra conversar?</default>
	</talk>
	<talk character="Angely">
		<default>Acho que não.</default>
	</talk>
	<talk character="Edmont">
		<default>Eu te levo em casa, Dara.</default>
	</talk>
	<teller>
		<default>Edmont beija Dara e sai com ela. Angely baixa a cabeça.</default>
	</teller>
	<talk character="Kat">
		<default>Você tá me enrolando!</default>
	</talk>
	<talk character="Derik">
		<default>Que??? Eu???</default>
	</talk>
	<talk character="Kat">
		<default>É, você disse que ia me apresentar sua família!</default>
	</talk>
	<talk character="Derik">
		<default>Eu preciso ir agora... Faz o seguinte, amanhã eu te levo na minha casa.</default>
	</talk>
	<talk character="Kat">
		<default>Jura?</default>
	</talk>
	<talk character="Derik">
		<default>Juro.</default>
	</talk>
	<teller>
		<default>Derik cruza os dedos atrás das costas. Depois, sai com Kat. Mel e Angely ficam sozinhos.</default>
	</teller>
	<talk character="Mel">
		<default>Viu isso?</default>
	</talk>
	<talk character="Angely">
		<default>Que?</default>
	</talk>
	<talk character="Mel">
		<default>Kat não conhece a família do Derik.</default>
	</talk>
	<talk character="Angely">
		<default>Acho que devem ser iguais a ele.</default>
	</talk>
	<talk character="Mel">
		<default>Mas então por que ele não leva ela pra conhecê-los?</default>
	</talk>
	<talk character="Angely">
		<default>Ele prometeu que...</default>
	</talk>
	<talk character="Mel">
		<default>Hahaha. Estava cruzando os dedos. Aliás, extremamente infantil essa.</default>
	</talk>
	<talk character="Angely">
		<default>Derik não faria isso.</default>
	</talk>
	<talk character="Mel">
		<default>Você acredita em todo mundo.</default>
	</talk>
	<talk character="Angely">
		<default>E se ele for o único na família com esse poder?</default>
	</talk>
	<talk character="Mel">
		<default>Se ele estiver escondendo isso da família, é só pedir pra ela não falar.</default>
	</talk>
	<talk character="Angely">
		<default>Mas e se a origem dele não for humana?</default>
	</talk>
	<talk character="Mel">
		<default>Tá achando que a família dele podem ser pássaros ou cães?</default>
	</talk>
	<talk character="Angely">
		<default>Não é impossível.</default>
	</talk>
	<talk character="Mel">
		<default>Então acho melhor conversarmos com ele.</default>
	</talk>
	<talk character="Angely">
		<default>Bom, como disse você uma vez, nós não nos alimentamos de brisa. Quer que eu faça alguma coisa pra comermos?</default>
	</talk>
	<teller>
		<default>Mel pára e pensa um instante.</default>
	</teller>
	<talk character="Mel">
		<default>Peça uma pizza.</default>
	</talk>
	<teller>
		<default>Três da tarde, dia seguinte. Eles se reúnem no escritório.</default>
	</teller>
	<talk character="Kat">
		<default>Meu sonho não ajuda.</default>
	</talk>
	<talk character="Angely">
		<default>Tem a ver com ele?</default>
	</talk>
	<talk character="Kat">
		<default>Tem, mas não ajuda em nada nossa decisão.</default>
	</talk>
	<talk character="Derik">
		<default>Que sonhou com o vampiro?</default>
	</talk>
	<talk character="Dara">
		<default>Então, o que vamos fazer?</default>
	</talk>
	<talk character="Edmont">
		<default>Ainda tem a minha idéia.</default>
	</talk>
	<talk character="Dara">
		<default>E se perguntássemos pro fantasma? Talvez ele saiba alguma coisa.</default>
	</talk>
	<talk character="Edmont">
		<default>Jak já foi embora com a tal da Sarah.</default>
		<teller>ele olha pra Angely</teller>
		<default>Não devia falar em fantasmas.</default>
	</talk>
	<talk character="Dara">
		<default>Desculpe.</default>
	</talk>
	<talk character="Angely">
		<default>Não foi nada.</default>
	</talk>
	<talk character="Kat">
		<default>Então?</default>
	</talk>
	<talk character="Derik">
		<default>Ainda não respondeu o que perguntei!</default>
	</talk>
	<talk character="Mel">
		<default>Gente, não vamos... Aliás, tá tudo fechado, luz acesa... Que isso???</default>
	</talk>
	<talk character="Zenon">
		<default>Não é minha intenção que isso incomode vocês.</default>
		<teller>sai de trás de uma estante</teller>
		<default>É que o contrário me incomodaria.</default>
	</talk>
	<talk character="Dara">
		<default>Mas como você...?</default>
	</talk>
	<talk character="Zenon">
		<default>"Volte ao meio-dia e pode entrar".</default>
		<teller>mostra uma capa</teller>
		<default>Será que meu voto conta?</default>
	</talk>
	<talk character="Edmont">
		<default>Não!</default>
	</talk>
	<talk character="Zenon">
		<default>Tá.</default>
		<teller>senta</teller>
		<default>Decidam logo, tenho mais o que fazer.</default>
	</talk>
	<talk character="Edmont">
		<default>Pronto, um vampiro folgado... Acabo já com isso!</default>
	</talk>
	<teller>
		<default>Edmont vai descer, mas Angely não deixa.</default>
	</teller>
	<talk character="Angely">
		<default>Não, Edmont.</default>
	</talk>
	<talk character="Edmont">
		<default>Por que não?!</default>
	</talk>
	<talk character="Angely">
		<default>É a única alternativa que temos.</default>
	</talk>
	<talk character="Zenon">
		<default>Um a zero.</default>
	</talk>
	<talk character="Edmont">
		<default>É um vampiro!</default>
	</talk>
	<talk character="Zenon">
		<default>Um a um.</default>
	</talk>
	<talk character="Angely">
		<default>Sabe grego?</default>
	</talk>
	<talk character="Zenon">
		<default>Onze a um.</default>
	</talk>
	<talk character="Edmont">
		<default>Cala a boca!</default>
	</talk>
	<talk character="Derik">
		<default>Tá contando em números binários?</default>
	</talk>
	<talk character="Zenon">
		<default>Se fosse o sistema binário, eu falaria dez depois de um, não onze.</default>
	</talk>
	<talk character="Kat">
		<default>Olha, eu não tô mais contra.</default>
	</talk>
	<talk character="Mel">
		<default>Venceu o a favor.</default>
	</talk>
	<talk character="Derik">
		<default>Por que não está mais contra ele???</default>
	</talk>
	<talk character="Kat">
		<default>Não estou é contra saber o que está escrito!</default>
	</talk>
	<talk character="Dara">
		<default>Gente, vamos parar e pensar???</default>
	</talk>
	<talk character="Mel">
		<default>Já está ganho nosso voto. Ele traduz e nós falamos pra ele.</default>
	</talk>
	<talk character="Kat">
		<default>Vou buscar lá em casa o...</default>
		<teller>Zenon mostra o CD e um disquete</teller>
		<default>...arquivo.</default>
	</talk>
	<talk character="Edmont">
		<default>Esse símbolo, eu já vi isso!</default>
	</talk>
	<teller>
		<default>Edmont toma o CD das mãos de Zenon.</default>
	</teller>
	<talk character="Zenon">
		<default>Delicadeza zero!</default>
	</talk>
	<talk character="Edmont">
		<default>Se quer um cara delicado, procura no bar gay.</default>
	</talk>
	<teller>
		<default>Edmont se lembra do símbolo. Angely também.</default>
	</teller>
	<talk character="Edmont">
		<default>Meu pai... Isso era do meu pai!</default>
	</talk>
	<talk character="Zenon">
		<default>Bom, isso já é uma dica pra entender o tal diário.</default>
	</talk>
	<talk character="Edmont">
		<default>Vai traduzir, nós falamos pra você de onde viemos e só isso.</default>
	</talk>
	<talk character="Zenon">
		<default>Tá.</default>
	</talk>
	<teller>
		<default>Quase todos saem do escritório, ficando apenas Zenon e Angely.</default>
	</teller>
	<talk character="Zenon">
		<default>Que foi? Tá com medo que eu roube alguma coisa?</default>
	</talk>
	<talk character="Angely">
		<default>Por que essa curiosidade?</default>
	</talk>
	<talk character="Zenon">
		<default>Digamos que depois de quase dois séculos fica-se com nada pra fazer.</default>
	</talk>
	<talk character="Angely">
		<default>Não parece só isso.</default>
	</talk>
	<teller>
		<default>Angely sai pela porta da varanda. Olha pra Edmont e Dara.</default>
	</teller>
	<talk character="Mel">
		<default>Gosta dela?</default>
	</talk>
	<talk character="Angely">
		<default>Eu? Não.</default>
	</talk>
	<talk character="Mel">
		<default>Não parece.</default>
	</talk>
	<teller>
		<default>Duas noites se passam. Na terceira, todos de volta ao escritório, Zenon acabou.</default>
	</teller>
	<talk character="Zenon">
		<default>Apenas li, como tínhamos combinado. Mas vão ter que me contar primeiro quem são pra entender direito o que tava escrito aqui.</default>
	</talk>
	<talk character="Edmont">
		<default>Mel.</default>
	</talk>
	<talk character="Mel">
		<default>Viemos de outro planeta.</default>
	</talk>
	<talk character="Zenon">
		<default>Que?</default>
	</talk>
	<talk character="Mel">
		<default>Saturno.</default>
	</talk>
	<talk character="Zenon">
		<default>Como assim?</default>
	</talk>
</story>